__init__.py
pacemaker/pacemaker.py
pacemaker_lite-0.1.3.dist-info/LICENSE
pacemaker_lite-0.1.3.dist-info/METADATA
pacemaker_lite-0.1.3.dist-info/WHEEL
pacemaker_lite-0.1.3.dist-info/top_level.txt
pacemaker_lite-0.1.3.dist-info/RECORD
