Metadata-Version: 2.1
Name: pacemaker-lite
Version: 0.1.3
Summary: For controlling the duration of iteration loops
Author-email: Brandon Rohrer <brohrer@gmail.com>
Project-URL: Repository, https://github.com/brohrer/pacemaker
Project-URL: Book Chapter, https://brandonrohrer.com/httyr2pdf
Classifier: Programming Language :: Python :: 3
Classifier: License :: OSI Approved :: MIT License
Classifier: Operating System :: OS Independent
Requires-Python: >=3.8
License-File: LICENSE
